{
  "pluginName": "tekton-client",
  "pluginRepository": "https://github.com/jenkinsci/tekton-client-plugin.git",
  "pluginVersion": "1.0.3",
  "rpuBaseline": "2.492",
  "migrationName": "Migrate to JUnit 5",
  "migrationDescription": "Migrate tests to JUnit5.",
  "tags": [
    "testing",
    "migration"
  ],
  "migrationId": "io.jenkins.tools.pluginmodernizer.MigrateToJUnit5",
  "pullRequestUrl": "https://github.com/jenkinsci/tekton-client-plugin/pull/386",
  "pullRequestStatus": "closed",
  "dryRun": false,
  "additions": 51,
  "deletions": 52,
  "changedFiles": 8,
  "key": "2025-06-18T20-02-14.json",
  "path": "metadata-plugin-modernizer/tekton-client/modernization-metadata",
  "checkRuns": {
    "Code Coverage": "success",
    "Jenkins": "failure",
    "Jenkins Security Scan": "success",
    "Tests / linux-21 / Build (linux-21)": "failure",
    "build (17)": "success",
    "javadoc": "success",
    "security-scan / scan": "success",
    "spotbugs": "success",
    "test (17)": "failure"
  },
  "checkRunsSummary": "failure",
  "defaultBranch": "main",
  "defaultBranchLatestCommitSha": "c1f2bbf55d5827e9f0355d86d124ca2ecb856996"
}