{
  "pluginName": "tuleap-oauth",
  "pluginRepository": "https://github.com/Raunak80Madan/tuleap-oauth-plugin.git",
  "pluginVersion": "1.1.21",
  "rpuBaseline": "2.492",
  "migrationName": "Upgrade to the next major parent version (5.X) requiring Jenkins 2.492 and Java 17",
  "migrationDescription": "Upgrade to the next major parent version (5.X) requiring Jenkins 2.492 and Java 17.",
  "tags": [
    "dependencies"
  ],
  "migrationId": "io.jenkins.tools.pluginmodernizer.UpgradeNextMajorParentVersion",
  "pullRequestUrl": "",
  "pullRequestStatus": "",
  "dryRun": true,
  "key": "2025-06-16T13-52-59.json",
  "path": "metadata-plugin-modernizer\\tuleap-oauth\\modernization-metadata"
}